hcipy/__init__.py
hcipy/_version.py
hcipy/dev.py
hcipy/_math/__init__.py
hcipy/_math/cpu.py
hcipy/_math/fft.py
hcipy/aperture/__init__.py
hcipy/aperture/generic.py
hcipy/aperture/realistic.py
hcipy/atmosphere/__init__.py
hcipy/atmosphere/atmospheric_model.py
hcipy/atmosphere/finite_atmospheric_layer.py
hcipy/atmosphere/infinite_atmospheric_layer.py
hcipy/atmosphere/modal_adaptive_optics_layer.py
hcipy/atmosphere/standard_atmosphere.py
hcipy/atmosphere/stored_atmospheric_layer.py
hcipy/config/__init__.py
hcipy/config/config.py
hcipy/config/default_config.yaml
hcipy/coronagraphy/__init__.py
hcipy/coronagraphy/apodizing_phase_plate.py
hcipy/coronagraphy/fqpm.py
hcipy/coronagraphy/knife_edge.py
hcipy/coronagraphy/lyot.py
hcipy/coronagraphy/multi_scale.py
hcipy/coronagraphy/perfect_coronagraph.py
hcipy/coronagraphy/shaped_pupil.py
hcipy/coronagraphy/vortex.py
hcipy/field/__init__.py
hcipy/field/cartesian_grid.py
hcipy/field/coordinates.py
hcipy/field/field.py
hcipy/field/grid.py
hcipy/field/operations.py
hcipy/field/polar_grid.py
hcipy/field/spherical_grid.py
hcipy/field/util.py
hcipy/fourier/__init__.py
hcipy/fourier/chirp_z_transform.py
hcipy/fourier/fast_fourier_transform.py
hcipy/fourier/fourier_operations.py
hcipy/fourier/fourier_transform.py
hcipy/fourier/matrix_fourier_transform.py
hcipy/fourier/naive_fourier_transform.py
hcipy/fourier/zoom_fast_fourier_transform.py
hcipy/interpolation/__init__.py
hcipy/interpolation/linear.py
hcipy/interpolation/nearest.py
hcipy/metrics/__init__.py
hcipy/metrics/contrast.py
hcipy/metrics/profile.py
hcipy/mode_basis/__init__.py
hcipy/mode_basis/disk_harmonic.py
hcipy/mode_basis/fourier.py
hcipy/mode_basis/gaussian_hermite.py
hcipy/mode_basis/gaussian_laguerre.py
hcipy/mode_basis/gaussian_pokes.py
hcipy/mode_basis/karhunen_loeve.py
hcipy/mode_basis/lp_fiber_modes.py
hcipy/mode_basis/mode_basis.py
hcipy/mode_basis/zernike.py
hcipy/optics/__init__.py
hcipy/optics/aberration.py
hcipy/optics/apodization.py
hcipy-0.6.0.dist-info/LICENSE
hcipy-0.6.0.dist-info/METADATA
hcipy-0.6.0.dist-info/WHEEL
hcipy-0.6.0.dist-info/top_level.txt
hcipy-0.6.0.dist-info/RECORD
