Metadata-Version: 2.1
Name: hcipy
Version: 0.6.0
Summary: A framework for performing optical propagation simulations, meant for high contrast imaging, in Python.
Author-email: Emiel Por <epor@stsci.edu>
License: MIT License
Project-URL: homepage, https://hcipy.org
Project-URL: documentation, https://docs.hcipy.org
Project-URL: repository, https://github.com/ehpor/hcipy
Classifier: Development Status :: 4 - Beta
Classifier: License :: OSI Approved :: MIT License
Classifier: Operating System :: OS Independent
Classifier: Programming Language :: Python :: 3
Classifier: Programming Language :: Python :: 3.7
Classifier: Programming Language :: Python :: 3.8
Classifier: Programming Language :: Python :: 3.9
Classifier: Programming Language :: Python :: 3.10
Classifier: Programming Language :: Python :: 3.11
Classifier: Topic :: Scientific/Engineering :: Astronomy
Requires-Python: >=3.7
License-File: LICENSE
Requires-Dist: numpy
Requires-Dist: scipy
Requires-Dist: matplotlib >=2.0.0
Requires-Dist: Pillow
Requires-Dist: pyyaml
Requires-Dist: astropy
Requires-Dist: imageio
Requires-Dist: xxhash
Requires-Dist: numexpr
Requires-Dist: importlib-metadata ; python_version < "3.7"
Requires-Dist: importlib-resources >=1.4 ; python_version < "3.9"
Requires-Dist: asdf <=2.10 ; python_version <= "3.7"
Requires-Dist: asdf ; python_version > "3.7"
Provides-Extra: dev
Requires-Dist: pytest ; extra == 'dev'
Requires-Dist: pytest-cov ; extra == 'dev'
Requires-Dist: mpmath ; extra == 'dev'
Requires-Dist: dill ; extra == 'dev'
Requires-Dist: flake8 ; extra == 'dev'
Provides-Extra: doc
Requires-Dist: numpydoc ; extra == 'doc'
Requires-Dist: sphinx-rtd-theme ; extra == 'doc'
Requires-Dist: nbsphinx ; extra == 'doc'
Requires-Dist: jupyter-client ; extra == 'doc'
Requires-Dist: ipykernel ; extra == 'doc'
Requires-Dist: poppy ; extra == 'doc'
Requires-Dist: nbclient ; extra == 'doc'
Requires-Dist: nbformat ; extra == 'doc'
Requires-Dist: nbconvert ; extra == 'doc'
Requires-Dist: sphinx-automodapi ; extra == 'doc'
Requires-Dist: progressbar2 ; extra == 'doc'
